rasters/CRS.py
rasters/__init__.py
rasters/bbox.py
rasters/bias_correct.py
rasters/center_aeqd.py
rasters/clip.py
rasters/constants.py
rasters/coordinate_array.py
rasters/kdtree.py
rasters/linear_downscale.py
rasters/local_UTM_proj4.py
rasters/local_UTM_proj4_from_lat_lon.py
rasters/mosaic.py
rasters/multi_point.py
rasters/multi_polygon.py
rasters/multi_raster.py
rasters/out_of_bounds_error.py
rasters/point.py
rasters/polygon.py
rasters/raster.py
rasters/raster_geolocation.py
rasters/raster_geometry.py
rasters/raster_grid.py
rasters/rasters.py
rasters/spatial_geometry.py
rasters/transform_xy.py
rasters/vector_geometry.py
rasters/version.py
rasters/where.py
rasters/wrap_geometry.py
rasters-1.16.1.dist-info/licenses/LICENSE
tests/test_import_dependencies.py
tests/test_import_rasters.py
tests/test_input.tif
tests/test_local_UTM_proj4.py
tests/test_open_geotiff.py
tests/test_raster_geometry_local_UTM_proj4.py
tests/test_subsetting.py
tests/test_transform_xy.py
tests/test_write_geotiff.py
rasters-1.16.1.dist-info/METADATA
rasters-1.16.1.dist-info/WHEEL
rasters-1.16.1.dist-info/top_level.txt
rasters-1.16.1.dist-info/RECORD
