Metadata-Version: 2.4
Name: rasters
Version: 1.16.1
Summary: raster processing toolkit
Author-email: Gregory Halverson <gregory.h.halverson@jpl.nasa.gov>
Project-URL: Homepage, https://github.com/python-rasters/rasters
Classifier: Programming Language :: Python :: 3
Classifier: Operating System :: OS Independent
Requires-Python: >=3.10
License-File: LICENSE
Requires-Dist: affine
Requires-Dist: astropy
Requires-Dist: ECOv002-calval-tables
Requires-Dist: geopandas
Requires-Dist: h5py
Requires-Dist: matplotlib
Requires-Dist: msgpack
Requires-Dist: msgpack_numpy
Requires-Dist: numpy
Requires-Dist: pandas
Requires-Dist: pillow
Requires-Dist: pykdtree>=1.3.11
Requires-Dist: pyproj
Requires-Dist: pyresample
Requires-Dist: pytest
Requires-Dist: rasterio
Requires-Dist: scikit-image
Requires-Dist: scipy
Requires-Dist: shapely
Requires-Dist: six
Provides-Extra: dev
Requires-Dist: build; extra == "dev"
Requires-Dist: jupyter; extra == "dev"
Requires-Dist: pytest>=6.0; extra == "dev"
Requires-Dist: pytest-cov; extra == "dev"
Requires-Dist: twine; extra == "dev"
Dynamic: license-file
